fastapi_boot/__init__.py
fastapi_boot/cli/__init__.py
fastapi_boot/cli/cli.py
fastapi_boot/cli/template.py
fastapi_boot/core/DI.py
fastapi_boot/core/__init__.py
fastapi_boot/core/const.py
fastapi_boot/core/helper.py
fastapi_boot/core/model.py
fastapi_boot/core/routing.py
fastapi_boot/core/util.py
fastapi_boot/tortoise_util/__init__.py
fastapi_boot/tortoise_util/decorator.py
fastapi_boot-0.0.356.dist-info/licenses/LICENSE
fastapi_boot-0.0.356.dist-info/METADATA
fastapi_boot-0.0.356.dist-info/WHEEL
fastapi_boot-0.0.356.dist-info/entry_points.txt
fastapi_boot-0.0.356.dist-info/top_level.txt
fastapi_boot-0.0.356.dist-info/RECORD
