Metadata-Version: 2.4
Name: fastapi_boot
Version: 0.0.356
Summary: FastAPI development toolkit
Author: hfdy0935
Author-email: hfdy09354121794@gmail.com
Project-URL: Repository, https://github.com/hfdy0935/fastapi_boot
Classifier: Programming Language :: Python :: 3
Classifier: License :: OSI Approved :: MIT License
Classifier: Operating System :: OS Independent
License-File: LICENSE
Requires-Dist: starlette<0.42.0,>=0.40.0
Requires-Dist: pydantic!=1.8,!=1.8.1,!=2.0.0,!=2.0.1,!=2.1.0,<3.0.0,>=1.7.4
Requires-Dist: typing-extensions>=4.8.0
Dynamic: author
Dynamic: author-email
Dynamic: classifier
Dynamic: description
Dynamic: description-content-type
Dynamic: license-file
Dynamic: project-url
Dynamic: requires-dist
Dynamic: summary
